LICENSE
MANIFEST.in
README.txt
setup.py
pbp/__init__.py
pbp.scripts.egg-info/PKG-INFO
pbp.scripts.egg-info/SOURCES.txt
pbp.scripts.egg-info/dependency_links.txt
pbp.scripts.egg-info/entry_points.txt
pbp.scripts.egg-info/namespace_packages.txt
pbp.scripts.egg-info/not-zip-safe
pbp.scripts.egg-info/requires.txt
pbp.scripts.egg-info/top_level.txt
pbp/scripts/__init__.py
pbp/scripts/__init__.pyc
pbp/scripts/gprof2dot.py
pbp/scripts/gprof2dot.pyc
pbp/scripts/hotshot2dot.py
pbp/scripts/hotshot2dot.pyc
pbp/scripts/hotshotmain.py
pbp/scripts/hotshotmain.pyc
pbp/scripts/profiler.py
pbp/scripts/profiler.pyc
pbp/scripts/pythonstartup.py
pbp/scripts/pythonstartup.pyc
pbp/scripts/docs/README.txt
pbp/scripts/tests/__init__.py
pbp/scripts/tests/__init__.pyc
pbp/scripts/tests/test_docs.py
pbp/scripts/tests/test_docs.pyc
pbp/scripts/tests/test_profiler.py
pbp/scripts/tests/test_profiler.pyc