Metadata-Version: 1.0
Name: pbp.scripts
Version: 0.2.5
Summary: Expert Python Programming - Contains scripts presented throughout the book
Home-page: UNKNOWN
Author: Tarek Ziade
Author-email: tarek@ziade.org
License: GPL
Platform: UNKNOWN
Classifier: Programming Language :: Python
Classifier: Topic :: Software Development :: Libraries :: Python Modules
